{
	"id": "rGjtJNUFn5RjW8v",
	"json": "{\"id\":\"rGjtJNUFn5RjW8v\",\"url\":\"https://pursuit.unimelb.edu.au/health-wellbeing\",\"uniqueKey\":\"https://pursuit.unimelb.edu.au/health-wellbeing\",\"method\":\"GET\",\"noRetry\":false,\"retryCount\":0,\"errorMessages\":[],\"headers\":{},\"userData\":{\"__crawlee\":{\"skipNavigation\":false,\"enqueueStrategy\":\"same-hostname\"}}}",
	"method": "GET",
	"orderNo": 1710900954242,
	"retryCount": 0,
	"uniqueKey": "https://pursuit.unimelb.edu.au/health-wellbeing",
	"url": "https://pursuit.unimelb.edu.au/health-wellbeing"
}